udemy/__init__.py
udemy/udemy.py
udemy-0.1.2.dist-info/LICENSE
udemy-0.1.2.dist-info/METADATA
udemy-0.1.2.dist-info/WHEEL
udemy-0.1.2.dist-info/top_level.txt
udemy-0.1.2.dist-info/RECORD
